flake8_balanced_wrapping.py
flake8_balanced_wrapping-0.1.7.dist-info/LICENSE
flake8_balanced_wrapping-0.1.7.dist-info/METADATA
flake8_balanced_wrapping-0.1.7.dist-info/WHEEL
flake8_balanced_wrapping-0.1.7.dist-info/entry_points.txt
flake8_balanced_wrapping-0.1.7.dist-info/top_level.txt
flake8_balanced_wrapping-0.1.7.dist-info/RECORD
