Metadata-Version: 2.1
Name: flake8-balanced-wrapping
Version: 0.1.7
Summary: A flake8 plugin that helps you wrap code with visual balance.
Home-page: https://github.com/PeterJCLaw/flake8-balanced-wrapping
Author: Peter Law
Author-email: PeterJCLaw@gmail.com
License: Apache 2.0
Project-URL: Issue tracker, https://github.com/PeterJCLaw/flake8-balanced-wrapping/issues
Platform: UNKNOWN
Classifier: Development Status :: 2 - Pre-Alpha
Classifier: Environment :: Console
Classifier: Natural Language :: English
Classifier: Operating System :: OS Independent
Classifier: Programming Language :: Python
Classifier: Programming Language :: Python :: 3 :: Only
Classifier: Programming Language :: Python :: 3.7
Classifier: Programming Language :: Python :: 3.8
Classifier: Programming Language :: Python :: 3.9
Classifier: Programming Language :: Python :: 3.10
Classifier: Programming Language :: Python :: 3.11
Classifier: Topic :: Software Development
License-File: LICENSE
Requires-Dist: asttokens <3,>=2.1.0
Requires-Dist: tuck <0.3,>=0.2
Requires-Dist: typing-extensions
